[
  {
    "korean": "삼거리",
    "romanization": "samgeori",
    "pos": "名词",
    "meaning": "三岔路口",
    "register": "中立",
    "example": "삼거리가 나오면 오른쪽으로 가세요.",
    "exampleTranslation": "看到三岔路口的话请往右走。",
    "sentenceType": "命令句（请求）",
    "formalityLevel": "非格式体敬语（해요体）",
    "grammarBreakdown": [
      {
        "text": "삼거리가",
        "meaning": "三岔路口",
        "note": "삼거리(三岔路口)+가(主格助词)",
        "isTarget": true
      },
      {
        "text": "나오면",
        "meaning": "出现的话",
        "note": "나오다(出现)的词干+ -면(如果……的话)"
      },
      {
        "text": "오른쪽으로",
        "meaning": "往右边",
        "note": "오른쪽(右边)+으로(方向助词)"
      },
      {
        "text": "가세요",
        "meaning": "请走",
        "note": "가다(去)的词干+ -시-（尊敬阶标记）+ -어요（请求/命令·非格式体敬语终结词尾）"
      }
    ]
  },
  {
    "korean": "서점",
    "romanization": "seojeom",
    "pos": "名词",
    "meaning": "书店",
    "register": "中立",
    "example": "서점에서 책을 골랐습니다.",
    "exampleTranslation": "在书店选了书。",
    "sentenceType": "陈述句",
    "formalityLevel": "格式体敬语（합니다体）",
    "grammarBreakdown": [
      {
        "text": "서점에서",
        "meaning": "在书店",
        "note": "서점(书店)+에서(处所助词)",
        "isTarget": true
      },
      {
        "text": "책을",
        "meaning": "书",
        "note": "책(书)+을(宾格助词)"
      },
      {
        "text": "골랐습니다",
        "meaning": "选了",
        "note": "고르다(选)的词干变化+ -았-（过去时标记）+ -습니다（陈述句·格式体敬语终结词尾）"
      }
    ]
  },
  {
    "korean": "서쪽",
    "romanization": "seojjok",
    "pos": "名词",
    "meaning": "西边",
    "register": "中立",
    "example": "해가 서쪽으로 집니다.",
    "exampleTranslation": "太阳向西边落下。",
    "sentenceType": "陈述句",
    "formalityLevel": "格式体敬语（합니다体）",
    "grammarBreakdown": [
      {
        "text": "해가",
        "meaning": "太阳",
        "note": "해(太阳)+가(主格助词)"
      },
      {
        "text": "서쪽으로",
        "meaning": "向西边",
        "note": "서쪽(西边)+으로(方向助词)",
        "isTarget": true
      },
      {
        "text": "집니다",
        "meaning": "落下",
        "note": "지다(落下)的词干+ -ㅂ니다（陈述句·格式体敬语终结词尾）"
      }
    ]
  },
  {
    "korean": "세탁소",
    "romanization": "setakso",
    "pos": "名词",
    "meaning": "洗衣店",
    "register": "中立",
    "example": "세탁소에 옷을 맡겼습니다.",
    "exampleTranslation": "把衣服送去了洗衣店。",
    "sentenceType": "陈述句",
    "formalityLevel": "格式体敬语（합니다体）",
    "grammarBreakdown": [
      {
        "text": "세탁소에",
        "meaning": "洗衣店",
        "note": "세탁소(洗衣店)+에(方向助词)",
        "isTarget": true
      },
      {
        "text": "옷을",
        "meaning": "衣服",
        "note": "옷(衣服)+을(宾格助词)"
      },
      {
        "text": "맡겼습니다",
        "meaning": "送去了（托付）",
        "note": "맡기다(托付)的词干+ -었-（过去时标记）+ -습니다（陈述句·格式体敬语终结词尾）"
      }
    ]
  },
  {
    "korean": "안",
    "romanization": "an",
    "pos": "名词",
    "meaning": "里面",
    "register": "中立",
    "homonymIndex": "01",
    "example": "가방 안에 책이 있습니다.",
    "exampleTranslation": "包里面有书。",
    "sentenceType": "陈述句",
    "formalityLevel": "格式体敬语（합니다体）",
    "grammarBreakdown": [
      {
        "text": "가방 안에",
        "meaning": "包里面",
        "note": "가방(包)+안(里面)+에(处所助词)",
        "isTarget": true
      },
      {
        "text": "책이",
        "meaning": "书",
        "note": "책(书)+이(主格助词)"
      },
      {
        "text": "있습니다",
        "meaning": "有",
        "note": "있다(有)+ -습니다（陈述句·格式体敬语终结词尾）"
      }
    ]
  },
  {
    "korean": "안쪽",
    "romanization": "anjjok",
    "pos": "名词",
    "meaning": "内侧",
    "register": "中立",
    "example": "안쪽으로 들어가세요.",
    "exampleTranslation": "请往里走。",
    "sentenceType": "命令句（请求）",
    "formalityLevel": "非格式体敬语（해요体）",
    "grammarBreakdown": [
      {
        "text": "안쪽으로",
        "meaning": "往内侧",
        "note": "안쪽(内侧)+으로(方向助词)",
        "isTarget": true
      },
      {
        "text": "들어가세요",
        "meaning": "请进去",
        "note": "들어가다(进去)的词干+ -시-（尊敬阶标记）+ -어요（请求/命令·非格式体敬语终结词尾）"
      }
    ]
  },
  {
    "korean": "앞",
    "romanization": "ap",
    "pos": "名词",
    "meaning": "前面",
    "register": "中立",
    "example": "학교 앞에서 만납시다.",
    "exampleTranslation": "我们在学校前面见面吧。",
    "sentenceType": "共动句",
    "formalityLevel": "格式体敬语（합니다体）",
    "grammarBreakdown": [
      {
        "text": "학교 앞에서",
        "meaning": "学校前面",
        "note": "학교(学校)+앞(前面)+에서(处所助词)",
        "isTarget": true
      },
      {
        "text": "만납시다",
        "meaning": "让我们见面吧",
        "note": "만나다(见面)的词干+ -ㅂ시다（共动句·格式体敬语终结词尾）"
      }
    ]
  },
  {
    "korean": "앞쪽",
    "romanization": "apjjok",
    "pos": "名词",
    "meaning": "前边",
    "register": "中立",
    "example": "앞쪽에 자리가 있습니다.",
    "exampleTranslation": "前边有座位。",
    "sentenceType": "陈述句",
    "formalityLevel": "格式体敬语（합니다体）",
    "grammarBreakdown": [
      {
        "text": "앞쪽에",
        "meaning": "前边",
        "note": "앞쪽(前边)+에(处所助词)",
        "isTarget": true
      },
      {
        "text": "자리가",
        "meaning": "座位",
        "note": "자리(座位)+가(主格助词)"
      },
      {
        "text": "있습니다",
        "meaning": "有",
        "note": "있다(有)+ -습니다（陈述句·格式体敬语终结词尾）"
      }
    ]
  },
  {
    "korean": "옆",
    "romanization": "yeop",
    "pos": "名词",
    "meaning": "旁边",
    "register": "中立",
    "example": "제 옆에 앉으세요.",
    "exampleTranslation": "请坐在我旁边。",
    "sentenceType": "命令句（请求）",
    "formalityLevel": "非格式体敬语（해요体）",
    "grammarBreakdown": [
      {
        "text": "제",
        "meaning": "我的",
        "note": "저의 缩略形式"
      },
      {
        "text": "옆에",
        "meaning": "旁边",
        "note": "옆(旁边)+에(处所助词)",
        "isTarget": true
      },
      {
        "text": "앉으세요",
        "meaning": "请坐",
        "note": "앉다(坐)的词干+ -으시-（尊敬阶标记）+ -어요（请求/命令·非格式体敬语终结词尾）"
      }
    ]
  },
  {
    "korean": "옆집",
    "romanization": "yeopjjip",
    "pos": "名词",
    "meaning": "隔壁家",
    "register": "中立",
    "example": "옆집에 새 이웃이 이사왔습니다.",
    "exampleTranslation": "隔壁搬来了新邻居。",
    "sentenceType": "陈述句",
    "formalityLevel": "格式体敬语（합니다体）",
    "grammarBreakdown": [
      {
        "text": "옆집에",
        "meaning": "隔壁家",
        "note": "옆집(隔壁家)+에(方向助词)",
        "isTarget": true
      },
      {
        "text": "새",
        "meaning": "新的",
        "note": "冠形词"
      },
      {
        "text": "이웃이",
        "meaning": "邻居",
        "note": "이웃(邻居)+이(主格助词)"
      },
      {
        "text": "이사왔습니다",
        "meaning": "搬来了",
        "note": "이사오다(搬来)的词干+ -았-（过去时标记）+ -습니다（陈述句·格式体敬语终结词尾）"
      }
    ]
  },
  {
    "korean": "오른쪽",
    "romanization": "oreunjjok",
    "pos": "名词",
    "meaning": "右边",
    "register": "中立",
    "example": "오른쪽으로 도세요.",
    "exampleTranslation": "请往右转。",
    "sentenceType": "命令句（请求）",
    "formalityLevel": "非格式体敬语（해요体）",
    "grammarBreakdown": [
      {
        "text": "오른쪽으로",
        "meaning": "往右边",
        "note": "오른쪽(右边)+으로(方向助词)",
        "isTarget": true
      },
      {
        "text": "도세요",
        "meaning": "请转",
        "note": "돌다(转)的词干+ -시-（尊敬阶标记）+ -어요（请求/命令·非格式体敬语终结词尾）"
      }
    ]
  },
  {
    "korean": "왼쪽",
    "romanization": "oenjjok",
    "pos": "名词",
    "meaning": "左边",
    "register": "中立",
    "example": "왼쪽에 편의점이 있습니다.",
    "exampleTranslation": "左边有便利店。",
    "sentenceType": "陈述句",
    "formalityLevel": "格式体敬语（합니다体）",
    "grammarBreakdown": [
      {
        "text": "왼쪽에",
        "meaning": "左边",
        "note": "왼쪽(左边)+에(处所助词)",
        "isTarget": true
      },
      {
        "text": "편의점이",
        "meaning": "便利店",
        "note": "편의점(便利店)+이(主格助词)"
      },
      {
        "text": "있습니다",
        "meaning": "有",
        "note": "있다(有)+ -습니다（陈述句·格式体敬语终结词尾）"
      }
    ]
  },
  {
    "korean": "우체국",
    "romanization": "ucheguk",
    "pos": "名词",
    "meaning": "邮局",
    "register": "中立",
    "example": "우체국에서 소포를 보냈습니다.",
    "exampleTranslation": "在邮局寄了包裹。",
    "sentenceType": "陈述句",
    "formalityLevel": "格式体敬语（합니다体）",
    "grammarBreakdown": [
      {
        "text": "우체국에서",
        "meaning": "在邮局",
        "note": "우체국(邮局)+에서(处所助词)",
        "isTarget": true
      },
      {
        "text": "소포를",
        "meaning": "包裹",
        "note": "소포(包裹)+를(宾格助词)"
      },
      {
        "text": "보냈습니다",
        "meaning": "寄了",
        "note": "보내다(寄)的词干+ -었-（过去时标记）+ -습니다（陈述句·格式体敬语终结词尾）"
      }
    ]
  },
  {
    "korean": "울산",
    "romanization": "ulsan",
    "pos": "名词",
    "meaning": "蔚山（地名）",
    "register": "中立",
    "example": "울산은 공업 도시입니다.",
    "exampleTranslation": "蔚山是工业城市。",
    "sentenceType": "陈述句",
    "formalityLevel": "格式体敬语（합니다体）",
    "grammarBreakdown": [
      {
        "text": "울산은",
        "meaning": "蔚山",
        "note": "울산(蔚山)+은(主题助词)",
        "isTarget": true
      },
      {
        "text": "공업 도시입니다",
        "meaning": "是工业城市",
        "note": "공업(工业)+도시(城市)+이다+ -ㅂ니다（陈述句·格式体敬语终结词尾）"
      }
    ]
  },
  {
    "korean": "위",
    "romanization": "wi",
    "pos": "名词",
    "meaning": "上面",
    "register": "中立",
    "example": "책상 위에 컵이 있습니다.",
    "exampleTranslation": "书桌上面有杯子。",
    "sentenceType": "陈述句",
    "formalityLevel": "格式体敬语（합니다体）",
    "grammarBreakdown": [
      {
        "text": "책상 위에",
        "meaning": "书桌上面",
        "note": "책상(书桌)+위(上面)+에(处所助词)",
        "isTarget": true
      },
      {
        "text": "컵이",
        "meaning": "杯子",
        "note": "컵(杯子)+이(主格助词)"
      },
      {
        "text": "있습니다",
        "meaning": "有",
        "note": "있다(有)+ -습니다（陈述句·格式体敬语终结词尾）"
      }
    ]
  },
  {
    "korean": "위쪽",
    "romanization": "wijjok",
    "pos": "名词",
    "meaning": "上方",
    "register": "中立",
    "example": "위쪽을 보세요.",
    "exampleTranslation": "请看上方。",
    "sentenceType": "命令句（请求）",
    "formalityLevel": "非格式体敬语（해요体）",
    "grammarBreakdown": [
      {
        "text": "위쪽을",
        "meaning": "上方",
        "note": "위쪽(上方)+을(宾格助词)",
        "isTarget": true
      },
      {
        "text": "보세요",
        "meaning": "请看",
        "note": "보다(看)的词干+ -시-（尊敬阶标记）+ -어요（请求/命令·非格式体敬语终结词尾）"
      }
    ]
  },
  {
    "korean": "유치원",
    "romanization": "yuchiwon",
    "pos": "名词",
    "meaning": "幼儿园",
    "register": "中立",
    "example": "동생이 유치원에 다닙니다.",
    "exampleTranslation": "弟弟/妹妹在上幼儿园。",
    "sentenceType": "陈述句",
    "formalityLevel": "格式体敬语（합니다体）",
    "grammarBreakdown": [
      {
        "text": "동생이",
        "meaning": "弟弟妹妹",
        "note": "동생(弟弟妹妹)+이(主格助词)"
      },
      {
        "text": "유치원에",
        "meaning": "幼儿园",
        "note": "유치원(幼儿园)+에(方向助词)",
        "isTarget": true
      },
      {
        "text": "다닙니다",
        "meaning": "上（学）",
        "note": "다니다(上学/通勤)的词干+ -ㅂ니다（陈述句·格式体敬语终结词尾）"
      }
    ]
  },
  {
    "korean": "육교",
    "romanization": "yukgyo",
    "pos": "名词",
    "meaning": "天桥",
    "register": "中立",
    "example": "육교를 건너서 왔습니다.",
    "exampleTranslation": "过了天桥来的。",
    "sentenceType": "陈述句",
    "formalityLevel": "格式体敬语（합니다体）",
    "grammarBreakdown": [
      {
        "text": "육교를",
        "meaning": "天桥",
        "note": "육교(天桥)+를(宾格助词)",
        "isTarget": true
      },
      {
        "text": "건너서",
        "meaning": "过了之后",
        "note": "건너다(过)的词干+ -어서(先后)"
      },
      {
        "text": "왔습니다",
        "meaning": "来了",
        "note": "오다(来)的词干+ -았-（过去时标记）+ -습니다（陈述句·格式体敬语终结词尾）"
      }
    ]
  },
  {
    "korean": "은행",
    "romanization": "eunhaeng",
    "pos": "名词",
    "meaning": "银行",
    "register": "中立",
    "example": "은행에 돈을 입금했습니다.",
    "exampleTranslation": "往银行存了钱。",
    "sentenceType": "陈述句",
    "formalityLevel": "格式体敬语（합니다体）",
    "grammarBreakdown": [
      {
        "text": "은행에",
        "meaning": "银行",
        "note": "은행(银行)+에(方向助词)",
        "isTarget": true
      },
      {
        "text": "돈을",
        "meaning": "钱",
        "note": "돈(钱)+을(宾格助词)"
      },
      {
        "text": "입금했습니다",
        "meaning": "存了（款）",
        "note": "입금하다(存款)的词干+ -았-（过去时标记）+ -습니다（陈述句·格式体敬语终结词尾）"
      }
    ]
  },
  {
    "korean": "인천",
    "romanization": "incheon",
    "pos": "名词",
    "meaning": "仁川（地名）",
    "register": "中立",
    "example": "인천에 국제공항이 있습니다.",
    "exampleTranslation": "仁川有国际机场。",
    "sentenceType": "陈述句",
    "formalityLevel": "格式体敬语（합니다体）",
    "grammarBreakdown": [
      {
        "text": "인천에",
        "meaning": "仁川",
        "note": "인천(仁川)+에(处所助词)",
        "isTarget": true
      },
      {
        "text": "국제공항이",
        "meaning": "国际机场",
        "note": "국제공항(国际机场)+이(主格助词)"
      },
      {
        "text": "있습니다",
        "meaning": "有",
        "note": "있다(有)+ -습니다（陈述句·格式体敬语终结词尾）"
      }
    ]
  },
  {
    "korean": "입구",
    "romanization": "ipgu",
    "pos": "名词",
    "meaning": "入口",
    "register": "中立",
    "example": "지하철 입구에서 만납시다.",
    "exampleTranslation": "我们在地铁入口见吧。",
    "sentenceType": "共动句",
    "formalityLevel": "格式体敬语（합니다体）",
    "grammarBreakdown": [
      {
        "text": "지하철 입구에서",
        "meaning": "地铁入口",
        "note": "지하철(地铁)+입구(入口)+에서(处所助词)",
        "isTarget": true
      },
      {
        "text": "만납시다",
        "meaning": "让我们见面吧",
        "note": "만나다(见面)的词干+ -ㅂ시다（共动句·格式体敬语终结词尾）"
      }
    ]
  },
  {
    "korean": "자리",
    "romanization": "jari",
    "pos": "名词",
    "meaning": "座位",
    "register": "中立",
    "example": "빈 자리에 앉았습니다.",
    "exampleTranslation": "坐在了空座位上。",
    "sentenceType": "陈述句",
    "formalityLevel": "格式体敬语（합니다体）",
    "grammarBreakdown": [
      {
        "text": "빈",
        "meaning": "空的",
        "note": "비다(空)的词干+ -ㄴ(冠形词形)"
      },
      {
        "text": "자리에",
        "meaning": "座位",
        "note": "자리(座位)+에(方向助词)",
        "isTarget": true
      },
      {
        "text": "앉았습니다",
        "meaning": "坐了",
        "note": "앉다(坐)的词干+ -았-（过去时标记）+ -습니다（陈述句·格式体敬语终结词尾）"
      }
    ]
  },
  {
    "korean": "장소",
    "romanization": "jangso",
    "pos": "名词",
    "meaning": "场所",
    "register": "中立",
    "example": "모임 장소를 정했습니다.",
    "exampleTranslation": "定好了聚会场所。",
    "sentenceType": "陈述句",
    "formalityLevel": "格式体敬语（합니다体）",
    "grammarBreakdown": [
      {
        "text": "모임 장소를",
        "meaning": "聚会场所",
        "note": "모임(聚会)+장소(场所)+를(宾格助词)",
        "isTarget": true
      },
      {
        "text": "정했습니다",
        "meaning": "定了",
        "note": "정하다(决定)的词干+ -았-（过去时标记）+ -습니다（陈述句·格式体敬语终结词尾）"
      }
    ]
  },
  {
    "korean": "정거장",
    "romanization": "jeonggeojang",
    "pos": "名词",
    "meaning": "车站",
    "register": "中立",
    "example": "다음 정거장에서 내리겠습니다.",
    "exampleTranslation": "下一站下车。",
    "sentenceType": "陈述句",
    "formalityLevel": "格式体敬语（합니다体）",
    "grammarBreakdown": [
      {
        "text": "다음 정거장에서",
        "meaning": "在下一站",
        "note": "다음(下一个)+정거장(车站)+에서(处所助词)",
        "isTarget": true
      },
      {
        "text": "내리겠습니다",
        "meaning": "会下车",
        "note": "내리다(下车)的词干+ -겠-（意志/将来）+ -습니다（陈述句·格式体敬语终结词尾）"
      }
    ]
  },
  {
    "korean": "정류장",
    "romanization": "jeongnyujang",
    "pos": "名词",
    "meaning": "（公交）站",
    "register": "中立",
    "example": "버스 정류장에서 기다립니다.",
    "exampleTranslation": "在公交站等着。",
    "sentenceType": "陈述句",
    "formalityLevel": "格式体敬语（합니다体）",
    "grammarBreakdown": [
      {
        "text": "버스 정류장에서",
        "meaning": "在公交站",
        "note": "버스(公交车)+정류장(站)+에서(处所助词)",
        "isTarget": true
      },
      {
        "text": "기다립니다",
        "meaning": "等待",
        "note": "기다리다(等待)的词干+ -ㅂ니다（陈述句·格式体敬语终结词尾）"
      }
    ]
  },
  {
    "korean": "정형외과",
    "romanization": "jeonghyeongoegwa",
    "pos": "名词",
    "meaning": "骨科",
    "register": "中立",
    "example": "다리를 다쳐서 정형외과에 갔습니다.",
    "exampleTranslation": "因为腿受伤去了骨科。",
    "sentenceType": "陈述句",
    "formalityLevel": "格式体敬语（합니다体）",
    "grammarBreakdown": [
      {
        "text": "다리를",
        "meaning": "腿",
        "note": "다리(腿)+를(宾格助词)"
      },
      {
        "text": "다쳐서",
        "meaning": "受伤了，所以",
        "note": "다치다(受伤)的词干+ -어서(因为)"
      },
      {
        "text": "정형외과에",
        "meaning": "骨科",
        "note": "정형외과(骨科)+에(方向助词)",
        "isTarget": true
      },
      {
        "text": "갔습니다",
        "meaning": "去了",
        "note": "가다(去)的词干+ -았-（过去时标记）+ -습니다（陈述句·格式体敬语终结词尾）"
      }
    ]
  },
  {
    "korean": "제주도",
    "romanization": "jejudo",
    "pos": "名词",
    "meaning": "济州岛",
    "register": "中立",
    "example": "제주도로 여행을 갑니다.",
    "exampleTranslation": "去济州岛旅行。",
    "sentenceType": "陈述句",
    "formalityLevel": "格式体敬语（합니다体）",
    "grammarBreakdown": [
      {
        "text": "제주도로",
        "meaning": "去济州岛",
        "note": "제주도(济州岛)+로(方向助词)",
        "isTarget": true
      },
      {
        "text": "여행을",
        "meaning": "旅行",
        "note": "여행(旅行)+을(宾格助词)"
      },
      {
        "text": "갑니다",
        "meaning": "去",
        "note": "가다(去)的词干+ -ㅂ니다（陈述句·格式体敬语终结词尾）"
      }
    ]
  },
  {
    "korean": "주변",
    "romanization": "jubyeon",
    "pos": "名词",
    "meaning": "周边",
    "register": "中立",
    "example": "학교 주변에 식당이 많습니다.",
    "exampleTranslation": "学校周边有很多餐厅。",
    "sentenceType": "陈述句",
    "formalityLevel": "格式体敬语（합니다体）",
    "grammarBreakdown": [
      {
        "text": "학교 주변에",
        "meaning": "学校周边",
        "note": "학교(学校)+주변(周边)+에(处所助词)",
        "isTarget": true
      },
      {
        "text": "식당이",
        "meaning": "餐厅",
        "note": "식당(餐厅)+이(主格助词)"
      },
      {
        "text": "많습니다",
        "meaning": "多",
        "note": "많다(多)的词干+ -습니다（陈述句·格式体敬语终结词尾）"
      }
    ]
  },
  {
    "korean": "주위",
    "romanization": "juwi",
    "pos": "名词",
    "meaning": "周围",
    "register": "中立",
    "example": "주위를 잘 살펴보세요.",
    "exampleTranslation": "请仔细看看周围。",
    "sentenceType": "命令句（请求）",
    "formalityLevel": "非格式体敬语（해요体）",
    "grammarBreakdown": [
      {
        "text": "주위를",
        "meaning": "周围",
        "note": "주위(周围)+를(宾格助词)",
        "isTarget": true
      },
      {
        "text": "잘",
        "meaning": "仔细地",
        "note": "副词"
      },
      {
        "text": "살펴보세요",
        "meaning": "请看看",
        "note": "살펴보다(察看)的词干+ -시-（尊敬阶标记）+ -어요（请求/命令·非格式体敬语终结词尾）"
      }
    ]
  },
  {
    "korean": "주차",
    "romanization": "jucha",
    "pos": "名词",
    "meaning": "停车",
    "register": "中立",
    "example": "여기에 주차하면 안 됩니다.",
    "exampleTranslation": "这里不能停车。",
    "sentenceType": "陈述句",
    "formalityLevel": "格式体敬语（합니다体）",
    "grammarBreakdown": [
      {
        "text": "여기에",
        "meaning": "这里",
        "note": "여기(这里)+에(方向助词)"
      },
      {
        "text": "주차하면",
        "meaning": "停车的话",
        "note": "주차하다(停车)的词干+ -면(如果……的话)",
        "isTarget": true
      },
      {
        "text": "안 됩니다",
        "meaning": "不可以",
        "note": "안(不)+되다(可以，允许)+ -ㅂ니다（陈述句·格式体敬语终结词尾）"
      }
    ]
  },
  {
    "korean": "중앙",
    "romanization": "jungang",
    "pos": "名词",
    "meaning": "中央",
    "register": "中立",
    "example": "무대 중앙에 서 있습니다.",
    "exampleTranslation": "站在舞台中央。",
    "sentenceType": "陈述句",
    "formalityLevel": "格式体敬语（합니다体）",
    "grammarBreakdown": [
      {
        "text": "무대 중앙에",
        "meaning": "舞台中央",
        "note": "무대(舞台)+중앙(中央)+에(处所助词)",
        "isTarget": true
      },
      {
        "text": "서 있습니다",
        "meaning": "站着",
        "note": "서다(站)的词干+ -아/어 있다(状态持续)+ -습니다（陈述句·格式体敬语终结词尾）"
      }
    ]
  },
  {
    "korean": "지방",
    "romanization": "jibang",
    "pos": "名词",
    "meaning": "地方（区域）",
    "register": "中立",
    "example": "남쪽 지방은 날씨가 따뜻합니다.",
    "exampleTranslation": "南方地区天气暖和。",
    "sentenceType": "陈述句",
    "formalityLevel": "格式体敬语（합니다体）",
    "grammarBreakdown": [
      {
        "text": "남쪽 지방은",
        "meaning": "南方地区",
        "note": "남쪽(南边)+지방(地方)+은(主题助词)",
        "isTarget": true
      },
      {
        "text": "날씨가",
        "meaning": "天气",
        "note": "날씨(天气)+가(主格助词)"
      },
      {
        "text": "따뜻합니다",
        "meaning": "暖和",
        "note": "따뜻하다(暖和)的词干+ -ㅂ니다（陈述句·格式体敬语终结词尾）"
      }
    ]
  },
  {
    "korean": "지하",
    "romanization": "jiha",
    "pos": "名词",
    "meaning": "地下",
    "register": "中立",
    "example": "지하로 내려갔습니다.",
    "exampleTranslation": "下到了地下。",
    "sentenceType": "陈述句",
    "formalityLevel": "格式体敬语（합니다体）",
    "grammarBreakdown": [
      {
        "text": "지하로",
        "meaning": "往地下",
        "note": "지하(地下)+로(方向助词)",
        "isTarget": true
      },
      {
        "text": "내려갔습니다",
        "meaning": "下去了",
        "note": "내려가다(下去)的词干+ -았-（过去时标记）+ -습니다（陈述句·格式体敬语终结词尾）"
      }
    ]
  },
  {
    "korean": "지하도",
    "romanization": "jihado",
    "pos": "名词",
    "meaning": "地下通道",
    "register": "中立",
    "example": "지하도를 건너서 갔습니다.",
    "exampleTranslation": "穿过地下通道去了。",
    "sentenceType": "陈述句",
    "formalityLevel": "格式体敬语（합니다体）",
    "grammarBreakdown": [
      {
        "text": "지하도를",
        "meaning": "地下通道",
        "note": "지하도(地下通道)+를(宾格助词)",
        "isTarget": true
      },
      {
        "text": "건너서",
        "meaning": "穿过之后",
        "note": "건너다(穿过)的词干+ -어서(先后)"
      },
      {
        "text": "갔습니다",
        "meaning": "去了",
        "note": "가다(去)的词干+ -았-（过去时标记）+ -습니다（陈述句·格式体敬语终结词尾）"
      }
    ]
  },
  {
    "korean": "지하철역",
    "romanization": "jihacheollyeok",
    "pos": "名词",
    "meaning": "地铁站",
    "register": "中立",
    "example": "지하철역에 도착했습니다.",
    "exampleTranslation": "到达地铁站了。",
    "sentenceType": "陈述句",
    "formalityLevel": "格式体敬语（합니다体）",
    "grammarBreakdown": [
      {
        "text": "지하철역에",
        "meaning": "地铁站",
        "note": "지하철역(地铁站)+에(方向助词)",
        "isTarget": true
      },
      {
        "text": "도착했습니다",
        "meaning": "到达了",
        "note": "도착하다(到达)的词干+ -았-（过去时标记）+ -습니다（陈述句·格式体敬语终结词尾）"
      }
    ]
  },
  {
    "korean": "체육관",
    "romanization": "cheyukgwan",
    "pos": "名词",
    "meaning": "体育馆",
    "register": "中立",
    "example": "체육관에서 농구를 합니다.",
    "exampleTranslation": "在体育馆打篮球。",
    "sentenceType": "陈述句",
    "formalityLevel": "格式体敬语（합니다体）",
    "grammarBreakdown": [
      {
        "text": "체육관에서",
        "meaning": "在体育馆",
        "note": "체육관(体育馆)+에서(处所助词)",
        "isTarget": true
      },
      {
        "text": "농구를",
        "meaning": "篮球",
        "note": "농구(篮球)+를(宾格助词)"
      },
      {
        "text": "합니다",
        "meaning": "做",
        "note": "하다(做)的词干+ -ㅂ니다（陈述句·格式体敬语终结词尾）"
      }
    ]
  },
  {
    "korean": "초등학교",
    "romanization": "chodeunghakgyo",
    "pos": "名词",
    "meaning": "小学",
    "register": "中立",
    "example": "동생이 초등학교에 입학했습니다.",
    "exampleTranslation": "弟弟/妹妹上小学了。",
    "sentenceType": "陈述句",
    "formalityLevel": "格式体敬语（합니다体）",
    "grammarBreakdown": [
      {
        "text": "동생이",
        "meaning": "弟弟妹妹",
        "note": "동생(弟弟妹妹)+이(主格助词)"
      },
      {
        "text": "초등학교에",
        "meaning": "小学",
        "note": "초등학교(小学)+에(方向助词)",
        "isTarget": true
      },
      {
        "text": "입학했습니다",
        "meaning": "入学了",
        "note": "입학하다(入学)的词干+ -았-（过去时标记）+ -습니다（陈述句·格式体敬语终结词尾）"
      }
    ]
  },
  {
    "korean": "카페",
    "romanization": "kape",
    "pos": "名词",
    "meaning": "咖啡厅",
    "register": "中立",
    "example": "카페에서 친구를 만났습니다.",
    "exampleTranslation": "在咖啡厅见了朋友。",
    "sentenceType": "陈述句",
    "formalityLevel": "格式体敬语（합니다体）",
    "grammarBreakdown": [
      {
        "text": "카페에서",
        "meaning": "在咖啡厅",
        "note": "카페(咖啡厅)+에서(处所助词)",
        "isTarget": true
      },
      {
        "text": "친구를",
        "meaning": "朋友",
        "note": "친구(朋友)+를(宾格助词)"
      },
      {
        "text": "만났습니다",
        "meaning": "见了",
        "note": "만나다(见面)的词干+ -았-（过去时标记）+ -습니다（陈述句·格式体敬语终结词尾）"
      }
    ]
  },
  {
    "korean": "터미널",
    "romanization": "teomineol",
    "pos": "名词",
    "meaning": "客运站",
    "register": "中立",
    "example": "터미널에서 버스를 탔습니다.",
    "exampleTranslation": "在客运站坐了公交车。",
    "sentenceType": "陈述句",
    "formalityLevel": "格式体敬语（합니다体）",
    "grammarBreakdown": [
      {
        "text": "터미널에서",
        "meaning": "在客运站",
        "note": "터미널(客运站)+에서(处所助词)",
        "isTarget": true
      },
      {
        "text": "버스를",
        "meaning": "公交车",
        "note": "버스(公交车)+를(宾格助词)"
      },
      {
        "text": "탔습니다",
        "meaning": "坐了",
        "note": "타다(乘坐)的词干+ -았-（过去时标记）+ -습니다（陈述句·格式体敬语终结词尾）"
      }
    ]
  },
  {
    "korean": "테니스장",
    "romanization": "teniseujang",
    "pos": "名词",
    "meaning": "网球场",
    "register": "中立",
    "example": "테니스장에서 연습했습니다.",
    "exampleTranslation": "在网球场练习了。",
    "sentenceType": "陈述句",
    "formalityLevel": "格式体敬语（합니다体）",
    "grammarBreakdown": [
      {
        "text": "테니스장에서",
        "meaning": "在网球场",
        "note": "테니스장(网球场)+에서(处所助词)",
        "isTarget": true
      },
      {
        "text": "연습했습니다",
        "meaning": "练习了",
        "note": "연습하다(练习)的词干+ -았-（过去时标记）+ -습니다（陈述句·格式体敬语终结词尾）"
      }
    ]
  },
  {
    "korean": "학교",
    "romanization": "hakgyo",
    "pos": "名词",
    "meaning": "学校",
    "register": "中立",
    "example": "저는 매일 학교에 다닙니다.",
    "exampleTranslation": "我每天上学。",
    "sentenceType": "陈述句",
    "formalityLevel": "格式体敬语（합니다体）",
    "grammarBreakdown": [
      {
        "text": "저는",
        "meaning": "我",
        "note": "저(我)+는(主题助词)"
      },
      {
        "text": "매일",
        "meaning": "每天",
        "note": "副词"
      },
      {
        "text": "학교에",
        "meaning": "学校",
        "note": "학교(学校)+에(方向助词)",
        "isTarget": true
      },
      {
        "text": "다닙니다",
        "meaning": "上（学）",
        "note": "다니다(上学/通勤)的词干+ -ㅂ니다（陈述句·格式体敬语终结词尾）"
      }
    ]
  },
  {
    "korean": "학원",
    "romanization": "hagwon",
    "pos": "名词",
    "meaning": "补习班",
    "register": "中立",
    "example": "영어 학원에 다니고 있습니다.",
    "exampleTranslation": "正在上英语补习班。",
    "sentenceType": "陈述句",
    "formalityLevel": "格式体敬语（합니다体）",
    "grammarBreakdown": [
      {
        "text": "영어 학원에",
        "meaning": "英语补习班",
        "note": "영어(英语)+학원(补习班)+에(方向助词)",
        "isTarget": true
      },
      {
        "text": "다니고 있습니다",
        "meaning": "正在上",
        "note": "다니다(上学/通勤)的词干+ -고 있다(正在)+ -습니다（陈述句·格式体敬语终结词尾）"
      }
    ]
  },
  {
    "korean": "한강",
    "romanization": "hangang",
    "pos": "名词",
    "meaning": "汉江",
    "register": "中立",
    "example": "한강에서 자전거를 탔습니다.",
    "exampleTranslation": "在汉江骑了自行车。",
    "sentenceType": "陈述句",
    "formalityLevel": "格式体敬语（합니다体）",
    "grammarBreakdown": [
      {
        "text": "한강에서",
        "meaning": "在汉江",
        "note": "한강(汉江)+에서(处所助词)",
        "isTarget": true
      },
      {
        "text": "자전거를",
        "meaning": "自行车",
        "note": "자전거(自行车)+를(宾格助词)"
      },
      {
        "text": "탔습니다",
        "meaning": "骑了",
        "note": "타다(骑)的词干+ -았-（过去时标记）+ -습니다（陈述句·格式体敬语终结词尾）"
      }
    ]
  },
  {
    "korean": "한옥",
    "romanization": "hanok",
    "pos": "名词",
    "meaning": "韩屋",
    "register": "中立",
    "example": "한옥에서 하룻밤을 묵었습니다.",
    "exampleTranslation": "在韩屋住了一晚。",
    "sentenceType": "陈述句",
    "formalityLevel": "格式体敬语（합니다体）",
    "grammarBreakdown": [
      {
        "text": "한옥에서",
        "meaning": "在韩屋",
        "note": "한옥(韩屋)+에서(处所助词)",
        "isTarget": true
      },
      {
        "text": "하룻밤을",
        "meaning": "一晚",
        "note": "하룻밤(一晚)+을(宾格助词)"
      },
      {
        "text": "묵었습니다",
        "meaning": "住了",
        "note": "묵다(住宿)的词干+ -었-（过去时标记）+ -습니다（陈述句·格式体敬语终结词尾）"
      }
    ]
  },
  {
    "korean": "헬스클럽",
    "romanization": "helseukeulleop",
    "pos": "名词",
    "meaning": "健身房",
    "register": "中立",
    "example": "헬스클럽에서 운동합니다.",
    "exampleTranslation": "在健身房运动。",
    "sentenceType": "陈述句",
    "formalityLevel": "格式体敬语（합니다体）",
    "grammarBreakdown": [
      {
        "text": "헬스클럽에서",
        "meaning": "在健身房",
        "note": "헬스클럽(健身房)+에서(处所助词)",
        "isTarget": true
      },
      {
        "text": "운동합니다",
        "meaning": "运动",
        "note": "운동하다(运动)的词干+ -ㅂ니다（陈述句·格式体敬语终结词尾）"
      }
    ]
  },
  {
    "korean": "호수",
    "romanization": "hosu",
    "pos": "名词",
    "meaning": "湖",
    "register": "中立",
    "example": "호수가 아주 맑습니다.",
    "exampleTranslation": "湖水很清澈。",
    "sentenceType": "陈述句",
    "formalityLevel": "格式体敬语（합니다体）",
    "grammarBreakdown": [
      {
        "text": "호수가",
        "meaning": "湖",
        "note": "호수(湖)+가(主格助词)",
        "isTarget": true
      },
      {
        "text": "아주",
        "meaning": "很",
        "note": "副词"
      },
      {
        "text": "맑습니다",
        "meaning": "清澈",
        "note": "맑다(清澈)的词干+ -습니다（陈述句·格式体敬语终结词尾）"
      }
    ]
  },
  {
    "korean": "호텔",
    "romanization": "hotel",
    "pos": "名词",
    "meaning": "酒店",
    "register": "中立",
    "example": "호텔에 묵었습니다.",
    "exampleTranslation": "住在了酒店。",
    "sentenceType": "陈述句",
    "formalityLevel": "格式体敬语（합니다体）",
    "grammarBreakdown": [
      {
        "text": "호텔에",
        "meaning": "酒店",
        "note": "호텔(酒店)+에(方向助词)",
        "isTarget": true
      },
      {
        "text": "묵었습니다",
        "meaning": "住了",
        "note": "묵다(住宿)的词干+ -었-（过去时标记）+ -습니다（陈述句·格式体敬语终结词尾）"
      }
    ]
  },
  {
    "korean": "횡단보도",
    "romanization": "hoengdanbodo",
    "pos": "名词",
    "meaning": "人行横道",
    "register": "中立",
    "example": "횡단보도를 건너세요.",
    "exampleTranslation": "请过人行横道。",
    "sentenceType": "命令句（请求）",
    "formalityLevel": "非格式体敬语（해요体）",
    "grammarBreakdown": [
      {
        "text": "횡단보도를",
        "meaning": "人行横道",
        "note": "횡단보도(人行横道)+를(宾格助词)",
        "isTarget": true
      },
      {
        "text": "건너세요",
        "meaning": "请过",
        "note": "건너다(过)的词干+ -시-（尊敬阶标记）+ -어요（请求/命令·非格式体敬语终结词尾）"
      }
    ]
  },
  {
    "korean": "휴게실",
    "romanization": "hyugesil",
    "pos": "名词",
    "meaning": "休息室",
    "register": "中立",
    "example": "휴게실에서 잠깐 쉬었습니다.",
    "exampleTranslation": "在休息室休息了一会儿。",
    "sentenceType": "陈述句",
    "formalityLevel": "格式体敬语（합니다体）",
    "grammarBreakdown": [
      {
        "text": "휴게실에서",
        "meaning": "在休息室",
        "note": "휴게실(休息室)+에서(处所助词)",
        "isTarget": true
      },
      {
        "text": "잠깐",
        "meaning": "一会儿",
        "note": "副词"
      },
      {
        "text": "쉬었습니다",
        "meaning": "休息了",
        "note": "쉬다(休息)的词干+ -었-（过去时标记）+ -습니다（陈述句·格式体敬语终结词尾）"
      }
    ]
  }
]